{
  "generatedAt": "2026-07-17T01:52:29.759Z",
  "results": {
    "1605": {
      "code": "1605",
      "name": "INPEX",
      "segment": "large",
      "price": 3441,
      "previousClose": 3391,
      "change": 50,
      "percentChange": 1.4744913005013272,
      "volume": 1221300,
      "isMarketOpen": true,
      "updatedAt": 1784253145773,
      "error": null
    },
    "2229": {
      "code": "2229",
      "name": "カルビー",
      "segment": "mid",
      "price": 3021,
      "previousClose": 2990.5,
      "change": 30.5,
      "percentChange": 1.019896338404949,
      "volume": 82200,
      "isMarketOpen": true,
      "updatedAt": 1784253148698,
      "error": null
    },
    "2269": {
      "code": "2269",
      "name": "明治ホールディングス",
      "segment": "mid",
      "price": 3836,
      "previousClose": 3756,
      "change": 80,
      "percentChange": 2.1299254526091587,
      "volume": 304300,
      "isMarketOpen": true,
      "updatedAt": 1784253148731,
      "error": null
    },
    "2413": {
      "code": "2413",
      "name": "エムスリー",
      "segment": "mid",
      "price": 1927,
      "previousClose": 1874.5,
      "change": 52.5,
      "percentChange": 2.8007468658308885,
      "volume": 1517200,
      "isMarketOpen": true,
      "updatedAt": 1784253148343,
      "error": null
    },
    "2768": {
      "code": "2768",
      "name": "双日",
      "segment": "mid",
      "price": 5126,
      "previousClose": 5054,
      "change": 72,
      "percentChange": 1.4246141669964385,
      "volume": 397500,
      "isMarketOpen": true,
      "updatedAt": 1784253148709,
      "error": null
    },
    "2802": {
      "code": "2802",
      "name": "味の素",
      "segment": "large",
      "price": 5194,
      "previousClose": 5615,
      "change": -421,
      "percentChange": -7.497773820124666,
      "volume": 1678700,
      "isMarketOpen": true,
      "updatedAt": 1784253146170,
      "error": null
    },
    "2871": {
      "code": "2871",
      "name": "ニチレイ",
      "segment": "mid",
      "price": 2123.5,
      "previousClose": 2111.5,
      "change": 12,
      "percentChange": 0.5683163627752783,
      "volume": 2145000,
      "isMarketOpen": true,
      "updatedAt": 1784253149157,
      "error": null
    },
    "2914": {
      "code": "2914",
      "name": "日本たばこ産業",
      "segment": "large",
      "price": 6374,
      "previousClose": 6101,
      "change": 273,
      "percentChange": 4.474676282576627,
      "volume": 3359900,
      "isMarketOpen": true,
      "updatedAt": 1784253144456,
      "error": null
    },
    "3038": {
      "code": "3038",
      "name": "神戸物産",
      "segment": "mid",
      "price": 2754.5,
      "previousClose": 2679,
      "change": 75.5,
      "percentChange": 2.8182157521463234,
      "volume": 504200,
      "isMarketOpen": true,
      "updatedAt": 1784253148696,
      "error": null
    },
    "3092": {
      "code": "3092",
      "name": "ZOZO",
      "segment": "mid",
      "price": 1205,
      "previousClose": 1166,
      "change": 39,
      "percentChange": 3.3447684391080617,
      "volume": 1172500,
      "isMarketOpen": true,
      "updatedAt": 1784253148262,
      "error": null
    },
    "3099": {
      "code": "3099",
      "name": "三越伊勢丹ホールディングス",
      "segment": "mid",
      "price": 3962,
      "previousClose": 3984,
      "change": -22,
      "percentChange": -0.5522088353413654,
      "volume": 439500,
      "isMarketOpen": true,
      "updatedAt": 1784253149743,
      "error": null
    },
    "3382": {
      "code": "3382",
      "name": "セブン&アイ・ホールディングス",
      "segment": "large",
      "price": 2078.5,
      "previousClose": 2013,
      "change": 65.5,
      "percentChange": 3.2538499751614505,
      "volume": 4015700,
      "isMarketOpen": true,
      "updatedAt": 1784253143978,
      "error": null
    },
    "4063": {
      "code": "4063",
      "name": "信越化学工業",
      "segment": "large",
      "price": 7206,
      "previousClose": 7340,
      "change": -134,
      "percentChange": -1.8256130790190734,
      "volume": 2529900,
      "isMarketOpen": true,
      "updatedAt": 1784253141785,
      "error": null
    },
    "4188": {
      "code": "4188",
      "name": "三菱ケミカルグループ",
      "segment": "mid",
      "price": 1173,
      "previousClose": 1161.5,
      "change": 11.5,
      "percentChange": 0.9900990099009901,
      "volume": 1443900,
      "isMarketOpen": true,
      "updatedAt": 1784253149139,
      "error": null
    },
    "4307": {
      "code": "4307",
      "name": "野村総合研究所",
      "segment": "mid",
      "price": 5096,
      "previousClose": 5037,
      "change": 59,
      "percentChange": 1.171332142148104,
      "volume": 767000,
      "isMarketOpen": true,
      "updatedAt": 1784253147064,
      "error": null
    },
    "4324": {
      "code": "4324",
      "name": "電通グループ",
      "segment": "mid",
      "price": 3513,
      "previousClose": 3356,
      "change": 157,
      "percentChange": 4.67818831942789,
      "volume": 462800,
      "isMarketOpen": true,
      "updatedAt": 1784253146640,
      "error": null
    },
    "4452": {
      "code": "4452",
      "name": "花王",
      "segment": "large",
      "price": 3334,
      "previousClose": 3223,
      "change": 111,
      "percentChange": 3.443996276760782,
      "volume": 980700,
      "isMarketOpen": true,
      "updatedAt": 1784253144465,
      "error": null
    },
    "4502": {
      "code": "4502",
      "name": "武田薬品工業",
      "segment": "large",
      "price": 5451,
      "previousClose": 5318,
      "change": 133,
      "percentChange": 2.500940203083866,
      "volume": 1752700,
      "isMarketOpen": true,
      "updatedAt": 1784253141807,
      "error": null
    },
    "4543": {
      "code": "4543",
      "name": "テルモ",
      "segment": "large",
      "price": 2261,
      "previousClose": 2213.5,
      "change": 47.5,
      "percentChange": 2.1459227467811157,
      "volume": 1717800,
      "isMarketOpen": true,
      "updatedAt": 1784253144540,
      "error": null
    },
    "4568": {
      "code": "4568",
      "name": "第一三共",
      "segment": "large",
      "price": 2789,
      "previousClose": 2691.5,
      "change": 97.5,
      "percentChange": 3.622515326026379,
      "volume": 2367600,
      "isMarketOpen": true,
      "updatedAt": 1784253142166,
      "error": null
    },
    "4661": {
      "code": "4661",
      "name": "オリエンタルランド",
      "segment": "large",
      "price": 2741.5,
      "previousClose": 2650,
      "change": 91.5,
      "percentChange": 3.4528301886792456,
      "volume": 2252000,
      "isMarketOpen": true,
      "updatedAt": 1784253146214,
      "error": null
    },
    "4755": {
      "code": "4755",
      "name": "楽天グループ",
      "segment": "mid",
      "price": 801.4,
      "previousClose": 798.1,
      "change": 3.2999999999999545,
      "percentChange": 0.4134820197970122,
      "volume": 4468700,
      "isMarketOpen": true,
      "updatedAt": 1784253148269,
      "error": null
    },
    "4768": {
      "code": "4768",
      "name": "大塚商会",
      "segment": "mid",
      "price": 3041,
      "previousClose": 2924,
      "change": 117,
      "percentChange": 4.001367989056088,
      "volume": 474100,
      "isMarketOpen": true,
      "updatedAt": 1784253148303,
      "error": null
    },
    "4901": {
      "code": "4901",
      "name": "富士フイルムホールディングス",
      "segment": "large",
      "price": 3643,
      "previousClose": 3566,
      "change": 77,
      "percentChange": 2.159282108805384,
      "volume": 1011900,
      "isMarketOpen": true,
      "updatedAt": 1784253144468,
      "error": null
    },
    "5020": {
      "code": "5020",
      "name": "ENEOSホールディングス",
      "segment": "large",
      "price": 1254,
      "previousClose": 1254.5,
      "change": -0.5,
      "percentChange": -0.03985651654045436,
      "volume": 1936600,
      "isMarketOpen": true,
      "updatedAt": 1784253145779,
      "error": null
    },
    "5108": {
      "code": "5108",
      "name": "ブリヂストン",
      "segment": "large",
      "price": 3740,
      "previousClose": 3579,
      "change": 161,
      "percentChange": 4.498463257893266,
      "volume": 1206600,
      "isMarketOpen": true,
      "updatedAt": 1784253144944,
      "error": null
    },
    "5401": {
      "code": "5401",
      "name": "日本製鉄",
      "segment": "large",
      "price": 584.2,
      "previousClose": 560,
      "change": 24.200000000000045,
      "percentChange": 4.321428571428579,
      "volume": 13879900,
      "isMarketOpen": true,
      "updatedAt": 1784253144953,
      "error": null
    },
    "5938": {
      "code": "5938",
      "name": "LIXIL",
      "segment": "mid",
      "price": 1893.5,
      "previousClose": 1838.5,
      "change": 55,
      "percentChange": 2.9915692140331793,
      "volume": 507400,
      "isMarketOpen": true,
      "updatedAt": 1784253147431,
      "error": null
    },
    "6098": {
      "code": "6098",
      "name": "リクルートホールディングス",
      "segment": "large",
      "price": 12735,
      "previousClose": 12350,
      "change": 385,
      "percentChange": 3.1174089068825914,
      "volume": 1212700,
      "isMarketOpen": true,
      "updatedAt": 1784253141750,
      "error": null
    },
    "6273": {
      "code": "6273",
      "name": "SMC",
      "segment": "large",
      "price": 70210,
      "previousClose": 73820,
      "change": -3610,
      "percentChange": -4.8902736385803305,
      "volume": 115500,
      "isMarketOpen": true,
      "updatedAt": 1784253144951,
      "error": null
    },
    "6367": {
      "code": "6367",
      "name": "ダイキン工業",
      "segment": "large",
      "price": 24530,
      "previousClose": 24990,
      "change": -460,
      "percentChange": -1.8407362945178072,
      "volume": 452100,
      "isMarketOpen": true,
      "updatedAt": 1784253144902,
      "error": null
    },
    "6479": {
      "code": "6479",
      "name": "ミネベアミツミ",
      "segment": "mid",
      "price": 3831,
      "previousClose": 4166,
      "change": -335,
      "percentChange": -8.041286605856937,
      "volume": 1286600,
      "isMarketOpen": true,
      "updatedAt": 1784253147843,
      "error": null
    },
    "6501": {
      "code": "6501",
      "name": "日立製作所",
      "segment": "large",
      "price": 4734,
      "previousClose": 4716,
      "change": 18,
      "percentChange": 0.38167938931297707,
      "volume": 3815500,
      "isMarketOpen": true,
      "updatedAt": 1784253142203,
      "error": null
    },
    "6503": {
      "code": "6503",
      "name": "三菱電機",
      "segment": "large",
      "price": 5386,
      "previousClose": 5647,
      "change": -261,
      "percentChange": -4.621923145032761,
      "volume": 2370200,
      "isMarketOpen": true,
      "updatedAt": 1784253142199,
      "error": null
    },
    "6526": {
      "code": "6526",
      "name": "ソシオネクスト",
      "segment": "mid",
      "price": 2273.5,
      "previousClose": 2677,
      "change": -403.5,
      "percentChange": -15.072842734404185,
      "volume": 4204500,
      "isMarketOpen": true,
      "updatedAt": 1784253146599,
      "error": null
    },
    "6586": {
      "code": "6586",
      "name": "マキタ",
      "segment": "mid",
      "price": 5558,
      "previousClose": 5548,
      "change": 10,
      "percentChange": 0.1802451333813987,
      "volume": 189700,
      "isMarketOpen": true,
      "updatedAt": 1784253148295,
      "error": null
    },
    "6594": {
      "code": "6594",
      "name": "ニデック",
      "segment": "large",
      "price": 2499,
      "previousClose": 2645,
      "change": -146,
      "percentChange": -5.51984877126654,
      "volume": 2799900,
      "isMarketOpen": true,
      "updatedAt": 1784253142573,
      "error": null
    },
    "6645": {
      "code": "6645",
      "name": "オムロン",
      "segment": "large",
      "price": 5308,
      "previousClose": 5623,
      "change": -315,
      "percentChange": -5.601991819313533,
      "volume": 492900,
      "isMarketOpen": true,
      "updatedAt": 1784253146264,
      "error": null
    },
    "6702": {
      "code": "6702",
      "name": "富士通",
      "segment": "large",
      "price": 3276,
      "previousClose": 3308,
      "change": -32,
      "percentChange": -0.9673518742442563,
      "volume": 3703700,
      "isMarketOpen": true,
      "updatedAt": 1784253142561,
      "error": null
    },
    "6723": {
      "code": "6723",
      "name": "ルネサスエレクトロニクス",
      "segment": "large",
      "price": 3832,
      "previousClose": 4469,
      "change": -637,
      "percentChange": -14.253748042067576,
      "volume": 5748000,
      "isMarketOpen": true,
      "updatedAt": 1784253143150,
      "error": null
    },
    "6724": {
      "code": "6724",
      "name": "セイコーエプソン",
      "segment": "mid",
      "price": 2817,
      "previousClose": 2790.5,
      "change": 26.5,
      "percentChange": 0.9496506002508511,
      "volume": 533600,
      "isMarketOpen": true,
      "updatedAt": 1784253147430,
      "error": null
    },
    "6752": {
      "code": "6752",
      "name": "パナソニックホールディングス",
      "segment": "large",
      "price": 4050,
      "previousClose": 4419,
      "change": -369,
      "percentChange": -8.350305498981669,
      "volume": 4044600,
      "isMarketOpen": true,
      "updatedAt": 1784253142659,
      "error": null
    },
    "6758": {
      "code": "6758",
      "name": "ソニーグループ",
      "segment": "large",
      "price": 3485,
      "previousClose": 3341,
      "change": 144,
      "percentChange": 4.310086800359174,
      "volume": 8192400,
      "isMarketOpen": true,
      "updatedAt": 1784253140942,
      "error": null
    },
    "6770": {
      "code": "6770",
      "name": "アルプスアルパイン",
      "segment": "mid",
      "price": 2059.5,
      "previousClose": 2073.5,
      "change": -14,
      "percentChange": -0.6751868820834338,
      "volume": 566500,
      "isMarketOpen": true,
      "updatedAt": 1784253147001,
      "error": null
    },
    "6841": {
      "code": "6841",
      "name": "横河電機",
      "segment": "mid",
      "price": 5481,
      "previousClose": 5577,
      "change": -96,
      "percentChange": -1.7213555675094134,
      "volume": 398500,
      "isMarketOpen": true,
      "updatedAt": 1784253147877,
      "error": null
    },
    "6857": {
      "code": "6857",
      "name": "アドバンテスト",
      "segment": "large",
      "price": 26770,
      "previousClose": 28820,
      "change": -2050,
      "percentChange": -7.113115891741846,
      "volume": 4852600,
      "isMarketOpen": true,
      "updatedAt": 1784253142618,
      "error": null
    },
    "6861": {
      "code": "6861",
      "name": "キーエンス",
      "segment": "large",
      "price": 71290,
      "previousClose": 76700,
      "change": -5410,
      "percentChange": -7.053455019556715,
      "volume": 279300,
      "isMarketOpen": true,
      "updatedAt": 1784253141356,
      "error": null
    },
    "6920": {
      "code": "6920",
      "name": "レーザーテック",
      "segment": "large",
      "price": 41740,
      "previousClose": 44770,
      "change": -3030,
      "percentChange": -6.767924949743131,
      "volume": 2093400,
      "isMarketOpen": true,
      "updatedAt": 1784253143185,
      "error": null
    },
    "6963": {
      "code": "6963",
      "name": "ローム",
      "segment": "mid",
      "price": 4587,
      "previousClose": 5243,
      "change": -656,
      "percentChange": -12.511920656112913,
      "volume": 2705500,
      "isMarketOpen": true,
      "updatedAt": 1784253147843,
      "error": null
    },
    "6971": {
      "code": "6971",
      "name": "京セラ",
      "segment": "large",
      "price": 3546,
      "previousClose": 3637,
      "change": -91,
      "percentChange": -2.5020621391256532,
      "volume": 1842400,
      "isMarketOpen": true,
      "updatedAt": 1784253144907,
      "error": null
    },
    "6976": {
      "code": "6976",
      "name": "太陽誘電",
      "segment": "mid",
      "price": 11070,
      "previousClose": 11900,
      "change": -830,
      "percentChange": -6.974789915966387,
      "volume": 10910900,
      "isMarketOpen": true,
      "updatedAt": 1784253147910,
      "error": null
    },
    "6981": {
      "code": "6981",
      "name": "村田製作所",
      "segment": "large",
      "price": 7700,
      "previousClose": 9066,
      "change": -1366,
      "percentChange": -15.067284359144054,
      "volume": 18106100,
      "isMarketOpen": true,
      "updatedAt": 1784253142744,
      "error": null
    },
    "7011": {
      "code": "7011",
      "name": "三菱重工業",
      "segment": "large",
      "price": 3701,
      "previousClose": 3758,
      "change": -57,
      "percentChange": -1.5167642362959022,
      "volume": 8742800,
      "isMarketOpen": true,
      "updatedAt": 1784253143108,
      "error": null
    },
    "7148": {
      "code": "7148",
      "name": "FPG",
      "segment": "mid",
      "price": 1588,
      "previousClose": 1566,
      "change": 22,
      "percentChange": 1.40485312899106,
      "volume": 136500,
      "isMarketOpen": true,
      "updatedAt": 1784253149174,
      "error": null
    },
    "7186": {
      "code": "7186",
      "name": "コンコルディア・フィナンシャルグループ",
      "segment": "mid",
      "price": 1829,
      "previousClose": 1885,
      "change": -56,
      "percentChange": -2.970822281167109,
      "volume": 1240800,
      "isMarketOpen": true,
      "updatedAt": 1784253146611,
      "error": null
    },
    "7201": {
      "code": "7201",
      "name": "日産自動車",
      "segment": "large",
      "price": 327.1,
      "previousClose": 305.1,
      "change": 22,
      "percentChange": 7.210750573582432,
      "volume": 11583700,
      "isMarketOpen": true,
      "updatedAt": 1784253142170,
      "error": null
    },
    "7202": {
      "code": "7202",
      "name": "いすゞ自動車",
      "segment": "mid",
      "price": 2332.5,
      "previousClose": 2319.5,
      "change": 13,
      "percentChange": 0.5604656175899978,
      "volume": 554700,
      "isMarketOpen": true,
      "updatedAt": 1784253147453,
      "error": null
    },
    "7203": {
      "code": "7203",
      "name": "トヨタ自動車",
      "segment": "large",
      "price": 2892,
      "previousClose": 2806,
      "change": 86,
      "percentChange": 3.0648610121168924,
      "volume": 14180500,
      "isMarketOpen": true,
      "updatedAt": 1784253140966,
      "error": null
    },
    "7261": {
      "code": "7261",
      "name": "マツダ",
      "segment": "mid",
      "price": 1130.5,
      "previousClose": 1101,
      "change": 29.5,
      "percentChange": 2.679382379654859,
      "volume": 2347400,
      "isMarketOpen": true,
      "updatedAt": 1784253147865,
      "error": null
    },
    "7267": {
      "code": "7267",
      "name": "本田技研工業",
      "segment": "large",
      "price": 1545.5,
      "previousClose": 1495,
      "change": 50.5,
      "percentChange": 3.3779264214046827,
      "volume": 3675400,
      "isMarketOpen": true,
      "updatedAt": 1784253142169,
      "error": null
    },
    "7269": {
      "code": "7269",
      "name": "スズキ",
      "segment": "large",
      "price": 2053.5,
      "previousClose": 2029.5,
      "change": 24,
      "percentChange": 1.1825572801182558,
      "volume": 1684300,
      "isMarketOpen": true,
      "updatedAt": 1784253146630,
      "error": null
    },
    "7270": {
      "code": "7270",
      "name": "SUBARU",
      "segment": "large",
      "price": 2529.5,
      "previousClose": 2475,
      "change": 54.5,
      "percentChange": 2.202020202020202,
      "volume": 1145200,
      "isMarketOpen": true,
      "updatedAt": 1784253143600,
      "error": null
    },
    "7283": {
      "code": "7283",
      "name": "アイシン",
      "segment": "mid",
      "price": 2290,
      "previousClose": 2432,
      "change": -142,
      "percentChange": -5.838815789473684,
      "volume": 88000,
      "isMarketOpen": true,
      "updatedAt": 1784253147480,
      "error": null
    },
    "7453": {
      "code": "7453",
      "name": "良品計画",
      "segment": "mid",
      "price": 4368,
      "previousClose": 4233,
      "change": 135,
      "percentChange": 3.1892274982282065,
      "volume": 2300000,
      "isMarketOpen": true,
      "updatedAt": 1784253149759,
      "error": null
    },
    "7459": {
      "code": "7459",
      "name": "メディパルホールディングス",
      "segment": "mid",
      "price": 2856,
      "previousClose": 2661,
      "change": 195,
      "percentChange": 7.328072153325817,
      "volume": 69100,
      "isMarketOpen": true,
      "updatedAt": 1784253148784,
      "error": null
    },
    "7733": {
      "code": "7733",
      "name": "オリンパス",
      "segment": "large",
      "price": 1774.5,
      "previousClose": 1775.5,
      "change": -1,
      "percentChange": -0.056322162771050406,
      "volume": 1792500,
      "isMarketOpen": true,
      "updatedAt": 1784253146174,
      "error": null
    },
    "7741": {
      "code": "7741",
      "name": "HOYA",
      "segment": "large",
      "price": 24985,
      "previousClose": 25480,
      "change": -495,
      "percentChange": -1.942700156985871,
      "volume": 274700,
      "isMarketOpen": true,
      "updatedAt": 1784253143149,
      "error": null
    },
    "7751": {
      "code": "7751",
      "name": "キヤノン",
      "segment": "large",
      "price": 4459,
      "previousClose": 4312,
      "change": 147,
      "percentChange": 3.4090909090909087,
      "volume": 2051900,
      "isMarketOpen": true,
      "updatedAt": 1784253143170,
      "error": null
    },
    "7832": {
      "code": "7832",
      "name": "バンダイナムコホールディングス",
      "segment": "mid",
      "price": 4231,
      "previousClose": 4065,
      "change": 166,
      "percentChange": 4.083640836408364,
      "volume": 741200,
      "isMarketOpen": true,
      "updatedAt": 1784253147021,
      "error": null
    },
    "8001": {
      "code": "8001",
      "name": "伊藤忠商事",
      "segment": "large",
      "price": 1910,
      "previousClose": 1877.5,
      "change": 32.5,
      "percentChange": 1.7310252996005324,
      "volume": 4387800,
      "isMarketOpen": true,
      "updatedAt": 1784253143564,
      "error": null
    },
    "8002": {
      "code": "8002",
      "name": "丸紅",
      "segment": "large",
      "price": 5045,
      "previousClose": 4862,
      "change": 183,
      "percentChange": 3.7638831756478814,
      "volume": 1480800,
      "isMarketOpen": true,
      "updatedAt": 1784253143994,
      "error": null
    },
    "8031": {
      "code": "8031",
      "name": "三井物産",
      "segment": "large",
      "price": 4718,
      "previousClose": 4580,
      "change": 138,
      "percentChange": 3.0131004366812224,
      "volume": 2560100,
      "isMarketOpen": true,
      "updatedAt": 1784253144100,
      "error": null
    },
    "8035": {
      "code": "8035",
      "name": "東京エレクトロン",
      "segment": "large",
      "price": 65060,
      "previousClose": 71300,
      "change": -6240,
      "percentChange": -8.751753155680223,
      "volume": 2578600,
      "isMarketOpen": true,
      "updatedAt": 1784253141795,
      "error": null
    },
    "8053": {
      "code": "8053",
      "name": "住友商事",
      "segment": "large",
      "price": 1537,
      "previousClose": 1555.5,
      "change": -18.5,
      "percentChange": -1.1893281902925106,
      "volume": 4142700,
      "isMarketOpen": true,
      "updatedAt": 1784253143986,
      "error": null
    },
    "8058": {
      "code": "8058",
      "name": "三菱商事",
      "segment": "large",
      "price": 4484,
      "previousClose": 4440,
      "change": 44,
      "percentChange": 0.990990990990991,
      "volume": 2354200,
      "isMarketOpen": true,
      "updatedAt": 1784253144018,
      "error": null
    },
    "8133": {
      "code": "8133",
      "name": "伊藤忠エネクス",
      "segment": "mid",
      "price": 2064,
      "previousClose": 2010,
      "change": 54,
      "percentChange": 2.6865671641791042,
      "volume": 40700,
      "isMarketOpen": true,
      "updatedAt": 1784253149315,
      "error": null
    },
    "8252": {
      "code": "8252",
      "name": "丸井グループ",
      "segment": "mid",
      "price": 3008,
      "previousClose": 2956,
      "change": 52,
      "percentChange": 1.7591339648173208,
      "volume": 247700,
      "isMarketOpen": true,
      "updatedAt": 1784253149704,
      "error": null
    },
    "8306": {
      "code": "8306",
      "name": "三菱UFJフィナンシャル・グループ",
      "segment": "large",
      "price": 3511,
      "previousClose": 3541,
      "change": -30,
      "percentChange": -0.8472182999152781,
      "volume": 23285800,
      "isMarketOpen": true,
      "updatedAt": 1784253141355,
      "error": null
    },
    "8316": {
      "code": "8316",
      "name": "三井住友フィナンシャルグループ",
      "segment": "large",
      "price": 6787,
      "previousClose": 6925,
      "change": -138,
      "percentChange": -1.992779783393502,
      "volume": 6097500,
      "isMarketOpen": true,
      "updatedAt": 1784253141346,
      "error": null
    },
    "8354": {
      "code": "8354",
      "name": "ふくおかフィナンシャルグループ",
      "segment": "mid",
      "price": 7212,
      "previousClose": 7334,
      "change": -122,
      "percentChange": -1.663485137714753,
      "volume": 483000,
      "isMarketOpen": true,
      "updatedAt": 1784253146623,
      "error": null
    },
    "8411": {
      "code": "8411",
      "name": "みずほフィナンシャルグループ",
      "segment": "large",
      "price": 8034,
      "previousClose": 8417,
      "change": -383,
      "percentChange": -4.550314839016276,
      "volume": 5083500,
      "isMarketOpen": true,
      "updatedAt": 1784253141341,
      "error": null
    },
    "8591": {
      "code": "8591",
      "name": "オリックス",
      "segment": "large",
      "price": 6310,
      "previousClose": 6391,
      "change": -81,
      "percentChange": -1.267407291503677,
      "volume": 1117400,
      "isMarketOpen": true,
      "updatedAt": 1784253145735,
      "error": null
    },
    "8604": {
      "code": "8604",
      "name": "野村ホールディングス",
      "segment": "large",
      "price": 1538,
      "previousClose": 1542.5,
      "change": -4.5,
      "percentChange": -0.2917341977309562,
      "volume": 5927700,
      "isMarketOpen": true,
      "updatedAt": 1784253146172,
      "error": null
    },
    "8725": {
      "code": "8725",
      "name": "MS&ADインシュアランスグループホールディングス",
      "segment": "large",
      "price": 4532,
      "previousClose": 4431,
      "change": 101,
      "percentChange": 2.279395170390431,
      "volume": 1446900,
      "isMarketOpen": true,
      "updatedAt": 1784253145328,
      "error": null
    },
    "8750": {
      "code": "8750",
      "name": "第一生命ホールディングス",
      "segment": "large",
      "price": 1809.5,
      "previousClose": 1828,
      "change": -18.5,
      "percentChange": -1.012035010940919,
      "volume": 2548000,
      "isMarketOpen": true,
      "updatedAt": 1784253145803,
      "error": null
    },
    "8766": {
      "code": "8766",
      "name": "東京海上ホールディングス",
      "segment": "large",
      "price": 7571,
      "previousClose": 7613,
      "change": -42,
      "percentChange": -0.5516879022724287,
      "volume": 1486000,
      "isMarketOpen": true,
      "updatedAt": 1784253145331,
      "error": null
    },
    "8801": {
      "code": "8801",
      "name": "三井不動産",
      "segment": "large",
      "price": 1561.5,
      "previousClose": 1517,
      "change": 44.5,
      "percentChange": 2.9334212261041532,
      "volume": 1902900,
      "isMarketOpen": true,
      "updatedAt": 1784253145372,
      "error": null
    },
    "8802": {
      "code": "8802",
      "name": "三菱地所",
      "segment": "large",
      "price": 4207,
      "previousClose": 4141,
      "change": 66,
      "percentChange": 1.5938179183772037,
      "volume": 590600,
      "isMarketOpen": true,
      "updatedAt": 1784253145313,
      "error": null
    },
    "8830": {
      "code": "8830",
      "name": "住友不動産",
      "segment": "large",
      "price": 3796,
      "previousClose": 3767,
      "change": 29,
      "percentChange": 0.7698433766923282,
      "volume": 501600,
      "isMarketOpen": true,
      "updatedAt": 1784253145327,
      "error": null
    },
    "9020": {
      "code": "9020",
      "name": "東日本旅客鉄道",
      "segment": "large",
      "price": 3661,
      "previousClose": 3531,
      "change": 130,
      "percentChange": 3.6816765788728403,
      "volume": 788900,
      "isMarketOpen": true,
      "updatedAt": 1784253143607,
      "error": null
    },
    "9022": {
      "code": "9022",
      "name": "東海旅客鉄道",
      "segment": "large",
      "price": 3788,
      "previousClose": 3657,
      "change": 131,
      "percentChange": 3.5821711785616626,
      "volume": 841300,
      "isMarketOpen": true,
      "updatedAt": 1784253143546,
      "error": null
    },
    "9202": {
      "code": "9202",
      "name": "ANAホールディングス",
      "segment": "large",
      "price": 3026,
      "previousClose": 3015,
      "change": 11,
      "percentChange": 0.3648424543946932,
      "volume": 718800,
      "isMarketOpen": true,
      "updatedAt": 1784253143624,
      "error": null
    },
    "9432": {
      "code": "9432",
      "name": "日本電信電話",
      "segment": "large",
      "price": 152.4,
      "previousClose": 149.1,
      "change": 3.3000000000000114,
      "percentChange": 2.213279678068418,
      "volume": 113912800,
      "isMarketOpen": true,
      "updatedAt": 1784253140939,
      "error": null
    },
    "9433": {
      "code": "9433",
      "name": "KDDI",
      "segment": "large",
      "price": 2894.5,
      "previousClose": 2809.5,
      "change": 85,
      "percentChange": 3.025449368214985,
      "volume": 3245600,
      "isMarketOpen": true,
      "updatedAt": 1784253140982,
      "error": null
    },
    "9434": {
      "code": "9434",
      "name": "ソフトバンク",
      "segment": "large",
      "price": 222.4,
      "previousClose": 214.6,
      "change": 7.800000000000011,
      "percentChange": 3.6346691519105363,
      "volume": 34354000,
      "isMarketOpen": true,
      "updatedAt": 1784253141404,
      "error": null
    },
    "9501": {
      "code": "9501",
      "name": "東京電力ホールディングス",
      "segment": "large",
      "price": 497.7,
      "previousClose": 485.3,
      "change": 12.399999999999977,
      "percentChange": 2.5551205439934015,
      "volume": 15223900,
      "isMarketOpen": true,
      "updatedAt": 1784253145770,
      "error": null
    },
    "9602": {
      "code": "9602",
      "name": "東宝",
      "segment": "mid",
      "price": 1436.5,
      "previousClose": 1350,
      "change": 86.5,
      "percentChange": 6.407407407407407,
      "volume": 2680500,
      "isMarketOpen": true,
      "updatedAt": 1784253149143,
      "error": null
    },
    "9684": {
      "code": "9684",
      "name": "スクウェア・エニックス・ホールディングス",
      "segment": "mid",
      "price": 2549.5,
      "previousClose": 2573,
      "change": -23.5,
      "percentChange": -0.9133307423241352,
      "volume": 236800,
      "isMarketOpen": true,
      "updatedAt": 1784253147420,
      "error": null
    },
    "9697": {
      "code": "9697",
      "name": "カプコン",
      "segment": "mid",
      "price": 3465,
      "previousClose": 3336,
      "change": 129,
      "percentChange": 3.8669064748201443,
      "volume": 1316300,
      "isMarketOpen": true,
      "updatedAt": 1784253146993,
      "error": null
    },
    "9766": {
      "code": "9766",
      "name": "コナミグループ",
      "segment": "mid",
      "price": 18985,
      "previousClose": 18535,
      "change": 450,
      "percentChange": 2.4278392230914485,
      "volume": 251700,
      "isMarketOpen": true,
      "updatedAt": 1784253146994,
      "error": null
    },
    "9831": {
      "code": "9831",
      "name": "ヤマダホールディングス",
      "segment": "mid",
      "price": 693.7,
      "previousClose": 662.5,
      "change": 31.200000000000045,
      "percentChange": 4.709433962264158,
      "volume": 1618700,
      "isMarketOpen": true,
      "updatedAt": 1784253149731,
      "error": null
    },
    "9843": {
      "code": "9843",
      "name": "ニトリホールディングス",
      "segment": "large",
      "price": 2471,
      "previousClose": 2397,
      "change": 74,
      "percentChange": 3.087192323738006,
      "volume": 713200,
      "isMarketOpen": true,
      "updatedAt": 1784253144512,
      "error": null
    },
    "9983": {
      "code": "9983",
      "name": "ファーストリテイリング",
      "segment": "large",
      "price": 80280,
      "previousClose": 81230,
      "change": -950,
      "percentChange": -1.1695186507447988,
      "volume": 616700,
      "isMarketOpen": true,
      "updatedAt": 1784253141804,
      "error": null
    },
    "9984": {
      "code": "9984",
      "name": "ソフトバンクグループ",
      "segment": "large",
      "price": 5447,
      "previousClose": 6364,
      "change": -917,
      "percentChange": -14.409176618478945,
      "volume": 23679300,
      "isMarketOpen": true,
      "updatedAt": 1784253140949,
      "error": null
    }
  }
}
