{
  "generatedAt": "2026-07-24T19:14:03.651Z",
  "results": {
    "1605": {
      "code": "1605",
      "name": "INPEX",
      "segment": "large",
      "price": 3761,
      "previousClose": 3401,
      "change": 360,
      "percentChange": 10.585122022934431,
      "volume": 6774300,
      "isMarketOpen": false,
      "updatedAt": 1784920439332,
      "error": null
    },
    "2229": {
      "code": "2229",
      "name": "カルビー",
      "segment": "mid",
      "price": 2940.5,
      "previousClose": 3003,
      "change": -62.5,
      "percentChange": -2.081252081252081,
      "volume": 286900,
      "isMarketOpen": false,
      "updatedAt": 1784920442725,
      "error": null
    },
    "2269": {
      "code": "2269",
      "name": "明治ホールディングス",
      "segment": "mid",
      "price": 3743,
      "previousClose": 3812,
      "change": -69,
      "percentChange": -1.8100734522560336,
      "volume": 851500,
      "isMarketOpen": false,
      "updatedAt": 1784920442683,
      "error": null
    },
    "2413": {
      "code": "2413",
      "name": "エムスリー",
      "segment": "mid",
      "price": 1820,
      "previousClose": 1919,
      "change": -99,
      "percentChange": -5.158936946326212,
      "volume": 2693000,
      "isMarketOpen": false,
      "updatedAt": 1784920442203,
      "error": null
    },
    "2768": {
      "code": "2768",
      "name": "双日",
      "segment": "mid",
      "price": 5390,
      "previousClose": 5072,
      "change": 318,
      "percentChange": 6.269716088328075,
      "volume": 912400,
      "isMarketOpen": false,
      "updatedAt": 1784920442724,
      "error": null
    },
    "2802": {
      "code": "2802",
      "name": "味の素",
      "segment": "large",
      "price": 5096,
      "previousClose": 5194,
      "change": -98,
      "percentChange": -1.8867924528301887,
      "volume": 3313400,
      "isMarketOpen": false,
      "updatedAt": 1784920439830,
      "error": null
    },
    "2871": {
      "code": "2871",
      "name": "ニチレイ",
      "segment": "mid",
      "price": 2150,
      "previousClose": 2135.5,
      "change": 14.5,
      "percentChange": 0.6789978927651603,
      "volume": 1483700,
      "isMarketOpen": false,
      "updatedAt": 1784920443181,
      "error": null
    },
    "2914": {
      "code": "2914",
      "name": "日本たばこ産業",
      "segment": "large",
      "price": 6461,
      "previousClose": 6347,
      "change": 114,
      "percentChange": 1.7961241531432173,
      "volume": 4635700,
      "isMarketOpen": false,
      "updatedAt": 1784920437996,
      "error": null
    },
    "3038": {
      "code": "3038",
      "name": "神戸物産",
      "segment": "mid",
      "price": 2659,
      "previousClose": 2719.5,
      "change": -60.5,
      "percentChange": -2.2246736532450817,
      "volume": 1363900,
      "isMarketOpen": false,
      "updatedAt": 1784920442671,
      "error": null
    },
    "3092": {
      "code": "3092",
      "name": "ZOZO",
      "segment": "mid",
      "price": 1124.5,
      "previousClose": 1193,
      "change": -68.5,
      "percentChange": -5.7418273260687345,
      "volume": 4712800,
      "isMarketOpen": false,
      "updatedAt": 1784920442228,
      "error": null
    },
    "3099": {
      "code": "3099",
      "name": "三越伊勢丹ホールディングス",
      "segment": "mid",
      "price": 3634,
      "previousClose": 3895,
      "change": -261,
      "percentChange": -6.700898587933247,
      "volume": 2975100,
      "isMarketOpen": false,
      "updatedAt": 1784920443577,
      "error": null
    },
    "3382": {
      "code": "3382",
      "name": "セブン&アイ・ホールディングス",
      "segment": "large",
      "price": 2146,
      "previousClose": 2080,
      "change": 66,
      "percentChange": 3.173076923076923,
      "volume": 10268100,
      "isMarketOpen": false,
      "updatedAt": 1784920437341,
      "error": null
    },
    "4063": {
      "code": "4063",
      "name": "信越化学工業",
      "segment": "large",
      "price": 6702,
      "previousClose": 7157,
      "change": -455,
      "percentChange": -6.357412323599274,
      "volume": 7678900,
      "isMarketOpen": false,
      "updatedAt": 1784920434933,
      "error": null
    },
    "4188": {
      "code": "4188",
      "name": "三菱ケミカルグループ",
      "segment": "mid",
      "price": 1189,
      "previousClose": 1168,
      "change": 21,
      "percentChange": 1.797945205479452,
      "volume": 7376200,
      "isMarketOpen": false,
      "updatedAt": 1784920443185,
      "error": null
    },
    "4307": {
      "code": "4307",
      "name": "野村総合研究所",
      "segment": "mid",
      "price": 4935,
      "previousClose": 5076,
      "change": -141,
      "percentChange": -2.7777777777777777,
      "volume": 1476500,
      "isMarketOpen": false,
      "updatedAt": 1784920440742,
      "error": null
    },
    "4324": {
      "code": "4324",
      "name": "電通グループ",
      "segment": "mid",
      "price": 3382,
      "previousClose": 3506,
      "change": -124,
      "percentChange": -3.5367940673131772,
      "volume": 759300,
      "isMarketOpen": false,
      "updatedAt": 1784920440315,
      "error": null
    },
    "4452": {
      "code": "4452",
      "name": "花王",
      "segment": "large",
      "price": 3223,
      "previousClose": 3308,
      "change": -85,
      "percentChange": -2.569528415961306,
      "volume": 2591400,
      "isMarketOpen": false,
      "updatedAt": 1784920437864,
      "error": null
    },
    "4502": {
      "code": "4502",
      "name": "武田薬品工業",
      "segment": "large",
      "price": 5648,
      "previousClose": 5480,
      "change": 168,
      "percentChange": 3.065693430656934,
      "volume": 3633100,
      "isMarketOpen": false,
      "updatedAt": 1784920434967,
      "error": null
    },
    "4543": {
      "code": "4543",
      "name": "テルモ",
      "segment": "large",
      "price": 2164.5,
      "previousClose": 2267.5,
      "change": -103,
      "percentChange": -4.5424476295479606,
      "volume": 2693400,
      "isMarketOpen": false,
      "updatedAt": 1784920437865,
      "error": null
    },
    "4568": {
      "code": "4568",
      "name": "第一三共",
      "segment": "large",
      "price": 2799.5,
      "previousClose": 2791,
      "change": 8.5,
      "percentChange": 0.3045503403797922,
      "volume": 4708200,
      "isMarketOpen": false,
      "updatedAt": 1784920435490,
      "error": null
    },
    "4661": {
      "code": "4661",
      "name": "オリエンタルランド",
      "segment": "large",
      "price": 2682.5,
      "previousClose": 2729.5,
      "change": -47,
      "percentChange": -1.7219270928741526,
      "volume": 4954000,
      "isMarketOpen": false,
      "updatedAt": 1784920439814,
      "error": null
    },
    "4755": {
      "code": "4755",
      "name": "楽天グループ",
      "segment": "mid",
      "price": 785.6,
      "previousClose": 799.1,
      "change": -13.5,
      "percentChange": -1.6894005756476034,
      "volume": 9816400,
      "isMarketOpen": false,
      "updatedAt": 1784920442268,
      "error": null
    },
    "4768": {
      "code": "4768",
      "name": "大塚商会",
      "segment": "mid",
      "price": 3026,
      "previousClose": 3015,
      "change": 11,
      "percentChange": 0.3648424543946932,
      "volume": 751100,
      "isMarketOpen": false,
      "updatedAt": 1784920442214,
      "error": null
    },
    "4901": {
      "code": "4901",
      "name": "富士フイルムホールディングス",
      "segment": "large",
      "price": 3626,
      "previousClose": 3633,
      "change": -7,
      "percentChange": -0.1926782273603083,
      "volume": 2351400,
      "isMarketOpen": false,
      "updatedAt": 1784920437891,
      "error": null
    },
    "5020": {
      "code": "5020",
      "name": "ENEOSホールディングス",
      "segment": "large",
      "price": 1320,
      "previousClose": 1243.5,
      "change": 76.5,
      "percentChange": 6.15199034981906,
      "volume": 8033300,
      "isMarketOpen": false,
      "updatedAt": 1784920439338,
      "error": null
    },
    "5108": {
      "code": "5108",
      "name": "ブリヂストン",
      "segment": "large",
      "price": 3716,
      "previousClose": 3729,
      "change": -13,
      "percentChange": -0.34861893268972916,
      "volume": 3446300,
      "isMarketOpen": false,
      "updatedAt": 1784920438402,
      "error": null
    },
    "5401": {
      "code": "5401",
      "name": "日本製鉄",
      "segment": "large",
      "price": 616.9,
      "previousClose": 585.6,
      "change": 31.299999999999955,
      "percentChange": 5.344945355191249,
      "volume": 58130400,
      "isMarketOpen": false,
      "updatedAt": 1784920438452,
      "error": null
    },
    "5938": {
      "code": "5938",
      "name": "LIXIL",
      "segment": "mid",
      "price": 1813.5,
      "previousClose": 1874.5,
      "change": -61,
      "percentChange": -3.254201120298746,
      "volume": 1668600,
      "isMarketOpen": false,
      "updatedAt": 1784920441238,
      "error": null
    },
    "6098": {
      "code": "6098",
      "name": "リクルートホールディングス",
      "segment": "large",
      "price": 12055,
      "previousClose": 12820,
      "change": -765,
      "percentChange": -5.967238689547582,
      "volume": 4119800,
      "isMarketOpen": false,
      "updatedAt": 1784920434957,
      "error": null
    },
    "6273": {
      "code": "6273",
      "name": "SMC",
      "segment": "large",
      "price": 70970,
      "previousClose": 69230,
      "change": 1740,
      "percentChange": 2.5133612595695505,
      "volume": 213600,
      "isMarketOpen": false,
      "updatedAt": 1784920438430,
      "error": null
    },
    "6367": {
      "code": "6367",
      "name": "ダイキン工業",
      "segment": "large",
      "price": 23880,
      "previousClose": 24500,
      "change": -620,
      "percentChange": -2.5306122448979593,
      "volume": 1112800,
      "isMarketOpen": false,
      "updatedAt": 1784920438422,
      "error": null
    },
    "6479": {
      "code": "6479",
      "name": "ミネベアミツミ",
      "segment": "mid",
      "price": 3879,
      "previousClose": 3821,
      "change": 58,
      "percentChange": 1.5179272441769172,
      "volume": 1994000,
      "isMarketOpen": false,
      "updatedAt": 1784920441766,
      "error": null
    },
    "6501": {
      "code": "6501",
      "name": "日立製作所",
      "segment": "large",
      "price": 4850,
      "previousClose": 4717,
      "change": 133,
      "percentChange": 2.8195887216451134,
      "volume": 7130900,
      "isMarketOpen": false,
      "updatedAt": 1784920435536,
      "error": null
    },
    "6503": {
      "code": "6503",
      "name": "三菱電機",
      "segment": "large",
      "price": 5650,
      "previousClose": 5370,
      "change": 280,
      "percentChange": 5.21415270018622,
      "volume": 3355200,
      "isMarketOpen": false,
      "updatedAt": 1784920435414,
      "error": null
    },
    "6526": {
      "code": "6526",
      "name": "ソシオネクスト",
      "segment": "mid",
      "price": 2392.5,
      "previousClose": 2266,
      "change": 126.5,
      "percentChange": 5.582524271844661,
      "volume": 5886700,
      "isMarketOpen": false,
      "updatedAt": 1784920440270,
      "error": null
    },
    "6586": {
      "code": "6586",
      "name": "マキタ",
      "segment": "mid",
      "price": 5623,
      "previousClose": 5568,
      "change": 55,
      "percentChange": 0.9877873563218391,
      "volume": 639400,
      "isMarketOpen": false,
      "updatedAt": 1784920442268,
      "error": null
    },
    "6594": {
      "code": "6594",
      "name": "ニデック",
      "segment": "large",
      "price": 2549,
      "previousClose": 2482,
      "change": 67,
      "percentChange": 2.6994359387590654,
      "volume": 4283400,
      "isMarketOpen": false,
      "updatedAt": 1784920435939,
      "error": null
    },
    "6645": {
      "code": "6645",
      "name": "オムロン",
      "segment": "large",
      "price": 5479,
      "previousClose": 5309,
      "change": 170,
      "percentChange": 3.2021096251648147,
      "volume": 739900,
      "isMarketOpen": false,
      "updatedAt": 1784920439768,
      "error": null
    },
    "6702": {
      "code": "6702",
      "name": "富士通",
      "segment": "large",
      "price": 3279,
      "previousClose": 3298,
      "change": -19,
      "percentChange": -0.5761067313523348,
      "volume": 4380600,
      "isMarketOpen": false,
      "updatedAt": 1784920435966,
      "error": null
    },
    "6723": {
      "code": "6723",
      "name": "ルネサスエレクトロニクス",
      "segment": "large",
      "price": 3928,
      "previousClose": 3822,
      "change": 106,
      "percentChange": 2.773417059131345,
      "volume": 11628500,
      "isMarketOpen": false,
      "updatedAt": 1784920436482,
      "error": null
    },
    "6724": {
      "code": "6724",
      "name": "セイコーエプソン",
      "segment": "mid",
      "price": 2922,
      "previousClose": 2813.5,
      "change": 108.5,
      "percentChange": 3.856406610982762,
      "volume": 931000,
      "isMarketOpen": false,
      "updatedAt": 1784920441236,
      "error": null
    },
    "6752": {
      "code": "6752",
      "name": "パナソニックホールディングス",
      "segment": "large",
      "price": 3883,
      "previousClose": 3993,
      "change": -110,
      "percentChange": -2.7548209366391188,
      "volume": 8822800,
      "isMarketOpen": false,
      "updatedAt": 1784920435959,
      "error": null
    },
    "6758": {
      "code": "6758",
      "name": "ソニーグループ",
      "segment": "large",
      "price": 3409,
      "previousClose": 3470,
      "change": -61,
      "percentChange": -1.7579250720461095,
      "volume": 10286800,
      "isMarketOpen": false,
      "updatedAt": 1784920434000,
      "error": null
    },
    "6770": {
      "code": "6770",
      "name": "アルプスアルパイン",
      "segment": "mid",
      "price": 2166,
      "previousClose": 2058.5,
      "change": 107.5,
      "percentChange": 5.222249210590236,
      "volume": 2318500,
      "isMarketOpen": false,
      "updatedAt": 1784920440747,
      "error": null
    },
    "6841": {
      "code": "6841",
      "name": "横河電機",
      "segment": "mid",
      "price": 5792,
      "previousClose": 5468,
      "change": 324,
      "percentChange": 5.92538405267008,
      "volume": 801900,
      "isMarketOpen": false,
      "updatedAt": 1784920441683,
      "error": null
    },
    "6857": {
      "code": "6857",
      "name": "アドバンテスト",
      "segment": "large",
      "price": 28945,
      "previousClose": 27505,
      "change": 1440,
      "percentChange": 5.235411743319396,
      "volume": 8849300,
      "isMarketOpen": false,
      "updatedAt": 1784920436005,
      "error": null
    },
    "6861": {
      "code": "6861",
      "name": "キーエンス",
      "segment": "large",
      "price": 71820,
      "previousClose": 70880,
      "change": 940,
      "percentChange": 1.3261851015801356,
      "volume": 618000,
      "isMarketOpen": false,
      "updatedAt": 1784920434450,
      "error": null
    },
    "6920": {
      "code": "6920",
      "name": "レーザーテック",
      "segment": "large",
      "price": 43170,
      "previousClose": 41890,
      "change": 1280,
      "percentChange": 3.055621866793984,
      "volume": 2812600,
      "isMarketOpen": false,
      "updatedAt": 1784920436421,
      "error": null
    },
    "6963": {
      "code": "6963",
      "name": "ローム",
      "segment": "mid",
      "price": 4688,
      "previousClose": 4531,
      "change": 157,
      "percentChange": 3.465018759655705,
      "volume": 3868000,
      "isMarketOpen": false,
      "updatedAt": 1784920441685,
      "error": null
    },
    "6971": {
      "code": "6971",
      "name": "京セラ",
      "segment": "large",
      "price": 3689,
      "previousClose": 3556,
      "change": 133,
      "percentChange": 3.740157480314961,
      "volume": 3336300,
      "isMarketOpen": false,
      "updatedAt": 1784920438438,
      "error": null
    },
    "6976": {
      "code": "6976",
      "name": "太陽誘電",
      "segment": "mid",
      "price": 11415,
      "previousClose": 11035,
      "change": 380,
      "percentChange": 3.4435885817852285,
      "volume": 19227600,
      "isMarketOpen": false,
      "updatedAt": 1784920441684,
      "error": null
    },
    "6981": {
      "code": "6981",
      "name": "村田製作所",
      "segment": "large",
      "price": 8311,
      "previousClose": 7632,
      "change": 679,
      "percentChange": 8.896750524109015,
      "volume": 22737700,
      "isMarketOpen": false,
      "updatedAt": 1784920436010,
      "error": null
    },
    "7011": {
      "code": "7011",
      "name": "三菱重工業",
      "segment": "large",
      "price": 3945,
      "previousClose": 3681,
      "change": 264,
      "percentChange": 7.171964140179298,
      "volume": 14576400,
      "isMarketOpen": false,
      "updatedAt": 1784920436470,
      "error": null
    },
    "7148": {
      "code": "7148",
      "name": "FPG",
      "segment": "mid",
      "price": 1593,
      "previousClose": 1566,
      "change": 27,
      "percentChange": 1.7241379310344827,
      "volume": 738500,
      "isMarketOpen": false,
      "updatedAt": 1784920443177,
      "error": null
    },
    "7186": {
      "code": "7186",
      "name": "コンコルディア・フィナンシャルグループ",
      "segment": "mid",
      "price": 1951.5,
      "previousClose": 1794,
      "change": 157.5,
      "percentChange": 8.779264214046822,
      "volume": 3475900,
      "isMarketOpen": false,
      "updatedAt": 1784920440295,
      "error": null
    },
    "7201": {
      "code": "7201",
      "name": "日産自動車",
      "segment": "large",
      "price": 322.2,
      "previousClose": 329.3,
      "change": -7.100000000000023,
      "percentChange": -2.1560886729426123,
      "volume": 31096500,
      "isMarketOpen": false,
      "updatedAt": 1784920435425,
      "error": null
    },
    "7202": {
      "code": "7202",
      "name": "いすゞ自動車",
      "segment": "mid",
      "price": 2272,
      "previousClose": 2323.5,
      "change": -51.5,
      "percentChange": -2.2164837529588985,
      "volume": 2058400,
      "isMarketOpen": false,
      "updatedAt": 1784920441185,
      "error": null
    },
    "7203": {
      "code": "7203",
      "name": "トヨタ自動車",
      "segment": "large",
      "price": 2897,
      "previousClose": 2899.5,
      "change": -2.5,
      "percentChange": -0.08622176237282289,
      "volume": 23007200,
      "isMarketOpen": false,
      "updatedAt": 1784920433989,
      "error": null
    },
    "7261": {
      "code": "7261",
      "name": "マツダ",
      "segment": "mid",
      "price": 1123,
      "previousClose": 1137,
      "change": -14,
      "percentChange": -1.2313104661389622,
      "volume": 9904800,
      "isMarketOpen": false,
      "updatedAt": 1784920441807,
      "error": null
    },
    "7267": {
      "code": "7267",
      "name": "本田技研工業",
      "segment": "large",
      "price": 1536,
      "previousClose": 1535.5,
      "change": 0.5,
      "percentChange": 0.0325626831650928,
      "volume": 9983700,
      "isMarketOpen": false,
      "updatedAt": 1784920435411,
      "error": null
    },
    "7269": {
      "code": "7269",
      "name": "スズキ",
      "segment": "large",
      "price": 1968.5,
      "previousClose": 2050.5,
      "change": -82,
      "percentChange": -3.999024628139478,
      "volume": 6786900,
      "isMarketOpen": false,
      "updatedAt": 1784920440288,
      "error": null
    },
    "7270": {
      "code": "7270",
      "name": "SUBARU",
      "segment": "large",
      "price": 2557,
      "previousClose": 2534,
      "change": 23,
      "percentChange": 0.9076558800315706,
      "volume": 3741700,
      "isMarketOpen": false,
      "updatedAt": 1784920436918,
      "error": null
    },
    "7283": {
      "code": "7283",
      "name": "アイシン",
      "segment": "mid",
      "price": 2293,
      "previousClose": 2249,
      "change": 44,
      "percentChange": 1.9564250778123609,
      "volume": 186700,
      "isMarketOpen": false,
      "updatedAt": 1784920441209,
      "error": null
    },
    "7453": {
      "code": "7453",
      "name": "良品計画",
      "segment": "mid",
      "price": 4202,
      "previousClose": 4259,
      "change": -57,
      "percentChange": -1.3383423338811928,
      "volume": 3123400,
      "isMarketOpen": false,
      "updatedAt": 1784920443650,
      "error": null
    },
    "7459": {
      "code": "7459",
      "name": "メディパルホールディングス",
      "segment": "mid",
      "price": 2876.5,
      "previousClose": 2848.5,
      "change": 28,
      "percentChange": 0.9829734948218362,
      "volume": 390500,
      "isMarketOpen": false,
      "updatedAt": 1784920442730,
      "error": null
    },
    "7733": {
      "code": "7733",
      "name": "オリンパス",
      "segment": "large",
      "price": 1729.5,
      "previousClose": 1771.5,
      "change": -42,
      "percentChange": -2.3708721422523285,
      "volume": 3047700,
      "isMarketOpen": false,
      "updatedAt": 1784920439796,
      "error": null
    },
    "7741": {
      "code": "7741",
      "name": "HOYA",
      "segment": "large",
      "price": 24560,
      "previousClose": 25215,
      "change": -655,
      "percentChange": -2.5976601229426928,
      "volume": 602200,
      "isMarketOpen": false,
      "updatedAt": 1784920436468,
      "error": null
    },
    "7751": {
      "code": "7751",
      "name": "キヤノン",
      "segment": "large",
      "price": 4526,
      "previousClose": 4466,
      "change": 60,
      "percentChange": 1.3434841021047919,
      "volume": 2647200,
      "isMarketOpen": false,
      "updatedAt": 1784920436468,
      "error": null
    },
    "7832": {
      "code": "7832",
      "name": "バンダイナムコホールディングス",
      "segment": "mid",
      "price": 4111,
      "previousClose": 4189,
      "change": -78,
      "percentChange": -1.862019575077584,
      "volume": 1280300,
      "isMarketOpen": false,
      "updatedAt": 1784920440769,
      "error": null
    },
    "8001": {
      "code": "8001",
      "name": "伊藤忠商事",
      "segment": "large",
      "price": 1957.5,
      "previousClose": 1902.5,
      "change": 55,
      "percentChange": 2.890932982917214,
      "volume": 10192000,
      "isMarketOpen": false,
      "updatedAt": 1784920436940,
      "error": null
    },
    "8002": {
      "code": "8002",
      "name": "丸紅",
      "segment": "large",
      "price": 5370,
      "previousClose": 4988,
      "change": 382,
      "percentChange": 7.658380112269447,
      "volume": 3407200,
      "isMarketOpen": false,
      "updatedAt": 1784920437429,
      "error": null
    },
    "8031": {
      "code": "8031",
      "name": "三井物産",
      "segment": "large",
      "price": 4966,
      "previousClose": 4662,
      "change": 304,
      "percentChange": 6.520806520806522,
      "volume": 5354900,
      "isMarketOpen": false,
      "updatedAt": 1784920437395,
      "error": null
    },
    "8035": {
      "code": "8035",
      "name": "東京エレクトロン",
      "segment": "large",
      "price": 62660,
      "previousClose": 65100,
      "change": -2440,
      "percentChange": -3.748079877112135,
      "volume": 3871900,
      "isMarketOpen": false,
      "updatedAt": 1784920434957,
      "error": null
    },
    "8053": {
      "code": "8053",
      "name": "住友商事",
      "segment": "large",
      "price": 1604,
      "previousClose": 1514,
      "change": 90,
      "percentChange": 5.9445178335535,
      "volume": 8791200,
      "isMarketOpen": false,
      "updatedAt": 1784920437395,
      "error": null
    },
    "8058": {
      "code": "8058",
      "name": "三菱商事",
      "segment": "large",
      "price": 4918,
      "previousClose": 4447,
      "change": 471,
      "percentChange": 10.591409939284912,
      "volume": 7225200,
      "isMarketOpen": false,
      "updatedAt": 1784920437379,
      "error": null
    },
    "8133": {
      "code": "8133",
      "name": "伊藤忠エネクス",
      "segment": "mid",
      "price": 2070,
      "previousClose": 2053,
      "change": 17,
      "percentChange": 0.8280565026790063,
      "volume": 243600,
      "isMarketOpen": false,
      "updatedAt": 1784920443145,
      "error": null
    },
    "8252": {
      "code": "8252",
      "name": "丸井グループ",
      "segment": "mid",
      "price": 2921.5,
      "previousClose": 2964,
      "change": -42.5,
      "percentChange": -1.4338731443994601,
      "volume": 742000,
      "isMarketOpen": false,
      "updatedAt": 1784920443616,
      "error": null
    },
    "8306": {
      "code": "8306",
      "name": "三菱UFJフィナンシャル・グループ",
      "segment": "large",
      "price": 3754,
      "previousClose": 3473,
      "change": 281,
      "percentChange": 8.090987618773395,
      "volume": 43056500,
      "isMarketOpen": false,
      "updatedAt": 1784920434438,
      "error": null
    },
    "8316": {
      "code": "8316",
      "name": "三井住友フィナンシャルグループ",
      "segment": "large",
      "price": 7161,
      "previousClose": 6721,
      "change": 440,
      "percentChange": 6.546644844517186,
      "volume": 9570300,
      "isMarketOpen": false,
      "updatedAt": 1784920434476,
      "error": null
    },
    "8354": {
      "code": "8354",
      "name": "ふくおかフィナンシャルグループ",
      "segment": "mid",
      "price": 7646,
      "previousClose": 7081,
      "change": 565,
      "percentChange": 7.979098997316764,
      "volume": 365700,
      "isMarketOpen": false,
      "updatedAt": 1784920440314,
      "error": null
    },
    "8411": {
      "code": "8411",
      "name": "みずほフィナンシャルグループ",
      "segment": "large",
      "price": 8652,
      "previousClose": 7930,
      "change": 722,
      "percentChange": 9.104665825977301,
      "volume": 9693400,
      "isMarketOpen": false,
      "updatedAt": 1784920434520,
      "error": null
    },
    "8591": {
      "code": "8591",
      "name": "オリックス",
      "segment": "large",
      "price": 6535,
      "previousClose": 6203,
      "change": 332,
      "percentChange": 5.352248911816862,
      "volume": 2486900,
      "isMarketOpen": false,
      "updatedAt": 1784920439348,
      "error": null
    },
    "8604": {
      "code": "8604",
      "name": "野村ホールディングス",
      "segment": "large",
      "price": 1600,
      "previousClose": 1520,
      "change": 80,
      "percentChange": 5.263157894736842,
      "volume": 9472200,
      "isMarketOpen": false,
      "updatedAt": 1784920439858,
      "error": null
    },
    "8725": {
      "code": "8725",
      "name": "MS&ADインシュアランスグループホールディングス",
      "segment": "large",
      "price": 4898,
      "previousClose": 4483,
      "change": 415,
      "percentChange": 9.257193843408432,
      "volume": 4857900,
      "isMarketOpen": false,
      "updatedAt": 1784920438846,
      "error": null
    },
    "8750": {
      "code": "8750",
      "name": "第一生命ホールディングス",
      "segment": "large",
      "price": 1925,
      "previousClose": 1799,
      "change": 126,
      "percentChange": 7.003891050583658,
      "volume": 10758100,
      "isMarketOpen": false,
      "updatedAt": 1784920439346,
      "error": null
    },
    "8766": {
      "code": "8766",
      "name": "東京海上ホールディングス",
      "segment": "large",
      "price": 8116,
      "previousClose": 7526,
      "change": 590,
      "percentChange": 7.839489768801489,
      "volume": 4747500,
      "isMarketOpen": false,
      "updatedAt": 1784920438884,
      "error": null
    },
    "8801": {
      "code": "8801",
      "name": "三井不動産",
      "segment": "large",
      "price": 1550,
      "previousClose": 1537,
      "change": 13,
      "percentChange": 0.8458035133376708,
      "volume": 6189300,
      "isMarketOpen": false,
      "updatedAt": 1784920438916,
      "error": null
    },
    "8802": {
      "code": "8802",
      "name": "三菱地所",
      "segment": "large",
      "price": 3990,
      "previousClose": 4112,
      "change": -122,
      "percentChange": -2.96692607003891,
      "volume": 3754700,
      "isMarketOpen": false,
      "updatedAt": 1784920438888,
      "error": null
    },
    "8830": {
      "code": "8830",
      "name": "住友不動産",
      "segment": "large",
      "price": 3680,
      "previousClose": 3764,
      "change": -84,
      "percentChange": -2.2316684378320937,
      "volume": 2911100,
      "isMarketOpen": false,
      "updatedAt": 1784920438855,
      "error": null
    },
    "9020": {
      "code": "9020",
      "name": "東日本旅客鉄道",
      "segment": "large",
      "price": 3632,
      "previousClose": 3624,
      "change": 8,
      "percentChange": 0.22075055187637968,
      "volume": 2596000,
      "isMarketOpen": false,
      "updatedAt": 1784920436931,
      "error": null
    },
    "9022": {
      "code": "9022",
      "name": "東海旅客鉄道",
      "segment": "large",
      "price": 3892,
      "previousClose": 3766,
      "change": 126,
      "percentChange": 3.3457249070631967,
      "volume": 3037400,
      "isMarketOpen": false,
      "updatedAt": 1784920436940,
      "error": null
    },
    "9202": {
      "code": "9202",
      "name": "ANAホールディングス",
      "segment": "large",
      "price": 2951,
      "previousClose": 3027,
      "change": -76,
      "percentChange": -2.510736703006277,
      "volume": 3206700,
      "isMarketOpen": false,
      "updatedAt": 1784920436926,
      "error": null
    },
    "9432": {
      "code": "9432",
      "name": "日本電信電話",
      "segment": "large",
      "price": 151.3,
      "previousClose": 151.1,
      "change": 0.20000000000001705,
      "percentChange": 0.13236267372602056,
      "volume": 183169900,
      "isMarketOpen": false,
      "updatedAt": 1784920434014,
      "error": null
    },
    "9433": {
      "code": "9433",
      "name": "KDDI",
      "segment": "large",
      "price": 2922.5,
      "previousClose": 2868,
      "change": 54.5,
      "percentChange": 1.900278940027894,
      "volume": 6594700,
      "isMarketOpen": false,
      "updatedAt": 1784920434002,
      "error": null
    },
    "9434": {
      "code": "9434",
      "name": "ソフトバンク",
      "segment": "large",
      "price": 221.6,
      "previousClose": 220.5,
      "change": 1.0999999999999943,
      "percentChange": 0.4988662131519248,
      "volume": 56673700,
      "isMarketOpen": false,
      "updatedAt": 1784920434422,
      "error": null
    },
    "9501": {
      "code": "9501",
      "name": "東京電力ホールディングス",
      "segment": "large",
      "price": 516.7,
      "previousClose": 506.6,
      "change": 10.100000000000023,
      "percentChange": 1.9936833793920294,
      "volume": 28624300,
      "isMarketOpen": false,
      "updatedAt": 1784920439362,
      "error": null
    },
    "9602": {
      "code": "9602",
      "name": "東宝",
      "segment": "mid",
      "price": 1446.5,
      "previousClose": 1430,
      "change": 16.5,
      "percentChange": 1.153846153846154,
      "volume": 6841800,
      "isMarketOpen": false,
      "updatedAt": 1784920443181,
      "error": null
    },
    "9684": {
      "code": "9684",
      "name": "スクウェア・エニックス・ホールディングス",
      "segment": "mid",
      "price": 2506.5,
      "previousClose": 2551,
      "change": -44.5,
      "percentChange": -1.7444139553116425,
      "volume": 657000,
      "isMarketOpen": false,
      "updatedAt": 1784920441233,
      "error": null
    },
    "9697": {
      "code": "9697",
      "name": "カプコン",
      "segment": "mid",
      "price": 3364,
      "previousClose": 3412,
      "change": -48,
      "percentChange": -1.406799531066823,
      "volume": 1941000,
      "isMarketOpen": false,
      "updatedAt": 1784920440725,
      "error": null
    },
    "9766": {
      "code": "9766",
      "name": "コナミグループ",
      "segment": "mid",
      "price": 18320,
      "previousClose": 18875,
      "change": -555,
      "percentChange": -2.9403973509933774,
      "volume": 418100,
      "isMarketOpen": false,
      "updatedAt": 1784920440774,
      "error": null
    },
    "9831": {
      "code": "9831",
      "name": "ヤマダホールディングス",
      "segment": "mid",
      "price": 724.5,
      "previousClose": 698.6,
      "change": 25.899999999999977,
      "percentChange": 3.7074148296593155,
      "volume": 4114000,
      "isMarketOpen": false,
      "updatedAt": 1784920443625,
      "error": null
    },
    "9843": {
      "code": "9843",
      "name": "ニトリホールディングス",
      "segment": "large",
      "price": 2407,
      "previousClose": 2459,
      "change": -52,
      "percentChange": -2.1146807645384302,
      "volume": 2396400,
      "isMarketOpen": false,
      "updatedAt": 1784920437871,
      "error": null
    },
    "9983": {
      "code": "9983",
      "name": "ファーストリテイリング",
      "segment": "large",
      "price": 76220,
      "previousClose": 78840,
      "change": -2620,
      "percentChange": -3.3231861998985286,
      "volume": 996400,
      "isMarketOpen": false,
      "updatedAt": 1784920434976,
      "error": null
    },
    "9984": {
      "code": "9984",
      "name": "ソフトバンクグループ",
      "segment": "large",
      "price": 5500,
      "previousClose": 5424,
      "change": 76,
      "percentChange": 1.4011799410029497,
      "volume": 43229200,
      "isMarketOpen": false,
      "updatedAt": 1784920433987,
      "error": null
    }
  }
}
